byteblower_test_framework/__init__.py
byteblower_test_framework/__main__.py
byteblower_test_framework/_scenario.py
byteblower_test_framework/_version.py
byteblower_test_framework/all.py
byteblower_test_framework/analysis.py
byteblower_test_framework/cli.py
byteblower_test_framework/constants.py
byteblower_test_framework/endpoint.py
byteblower_test_framework/exceptions.py
byteblower_test_framework/factory.py
byteblower_test_framework/host.py
byteblower_test_framework/logging.py
byteblower_test_framework/report.py
byteblower_test_framework/run.py
byteblower_test_framework/traffic.py
byteblower_test_framework/_analysis/__init__.py
byteblower_test_framework/_analysis/analyseraggregator.py
byteblower_test_framework/_analysis/bufferanalyser.py
byteblower_test_framework/_analysis/flow_analyser.py
byteblower_test_framework/_analysis/framelossanalyser.py
byteblower_test_framework/_analysis/helpers.py
byteblower_test_framework/_analysis/httpanalyser.py
byteblower_test_framework/_analysis/latencyaggregator.py
byteblower_test_framework/_analysis/latencyanalyser.py
byteblower_test_framework/_analysis/voiceanalyser.py
byteblower_test_framework/_analysis/data_analysis/__init__.py
byteblower_test_framework/_analysis/data_analysis/data_analyser.py
byteblower_test_framework/_analysis/data_analysis/frameblasting.py
byteblower_test_framework/_analysis/data_analysis/tcp.py
byteblower_test_framework/_analysis/data_gathering/__init__.py
byteblower_test_framework/_analysis/data_gathering/_filter.py
byteblower_test_framework/_analysis/data_gathering/_rx_trigger_controller.py
byteblower_test_framework/_analysis/data_gathering/data_gatherer.py
byteblower_test_framework/_analysis/data_gathering/stream.py
byteblower_test_framework/_analysis/data_gathering/tcp.py
byteblower_test_framework/_analysis/data_gathering/trigger.py
byteblower_test_framework/_analysis/plotting/__init__.py
byteblower_test_framework/_analysis/plotting/generic_chart.py
byteblower_test_framework/_analysis/render/__init__.py
byteblower_test_framework-1.3.3.dist-info/entry_points.txt
byteblower_test_framework-1.3.3.dist-info/LICENSE
byteblower_test_framework-1.3.3.dist-info/WHEEL
byteblower_test_framework-1.3.3.dist-info/METADATA
byteblower_test_framework-1.3.3.dist-info/RECORD
