Metadata-Version: 2.1
Name: byteblower-test-framework
Version: 1.3.3
Summary: Test Framework for the ByteBlower Traffic Generator.
Keywords: ByteBlower,Test Framework
Author-email: ByteBlower Development Team <support.byteblower@excentis.com>
Maintainer-email: Tom Ghyselinck <tom.ghyselinck@excentis.com>
Requires-Python: >=3.7
Classifier: Development Status :: 5 - Production/Stable
Classifier: Intended Audience :: Developers
Classifier: Intended Audience :: Information Technology
Classifier: Intended Audience :: Manufacturing
Classifier: Intended Audience :: Other Audience
Classifier: Intended Audience :: Science/Research
Classifier: Intended Audience :: Telecommunications Industry
Classifier: License :: OSI Approved :: GNU Lesser General Public License v3 (LGPLv3)
Classifier: Operating System :: OS Independent
Classifier: Programming Language :: Python
Classifier: Programming Language :: Python :: 3
Classifier: Programming Language :: Python :: 3.7
Classifier: Programming Language :: Python :: 3.8
Classifier: Programming Language :: Python :: 3.9
Classifier: Programming Language :: Python :: 3.10
Classifier: Programming Language :: Python :: 3.11
Classifier: Topic :: Software Development
Classifier: Topic :: Software Development :: Testing
Classifier: Topic :: Software Development :: Testing :: Traffic Generation
Classifier: Topic :: Software Development :: Libraries
Classifier: Topic :: Software Development :: Libraries :: Python Modules
Requires-Dist: byteblowerll >=2.19.2a114
Requires-Dist: scapy >=2.2.0
Requires-Dist: junit_xml >=1.8.0
Requires-Dist: pandas >=0.24.2
Requires-Dist: jinja2 >=2.10.1
Requires-Dist: highcharts-excentis >=0.4.4
Requires-Dist: pre-commit ; extra == "dev"
Requires-Dist: yapf[pyproject] ; extra == "dev"
Requires-Dist: isort ; extra == "dev"
Requires-Dist: rstcheck[toml] ; extra == "dev"
Requires-Dist: doc8 ; extra == "dev"
Requires-Dist: Pygments ; extra == "dev"
Requires-Dist: pydocstyle[toml] ; extra == "dev"
Requires-Dist: toml ~=0.10.2 ; extra == "dev"
Requires-Dist: Sphinx >= 5.0 ; extra == "docs-dev"
Requires-Dist: sphinx-rtd-theme >=1.0 ; extra == "docs-dev"
Requires-Dist: sphinx-tabs >= 3.4 ; extra == "docs-dev"
Requires-Dist: sphinx-tags >= 0.3.1 ; extra == "docs-dev"
Requires-Dist: sphinx-design >= 0.5.0 ; extra == "docs-dev"
Requires-Dist: sphinx-jsonschema >= 1.19 ; extra == "docs-dev"
Requires-Dist: importlib-metadata>=4.8.3 ; extra == "docs-dev" and ( python_version<'3.8')
Requires-Dist: rstcheck[sphinx,toml] ; extra == "docs-dev"
Requires-Dist: pylint[spelling] ; extra == "test"
Requires-Dist: pydocstyle[toml] ; extra == "test"
Requires-Dist: rstcheck[sphinx,toml] ; extra == "test"
Requires-Dist: mypy >=1.0.0 ; extra == "test"
Requires-Dist: pandas-stubs ; extra == "test"
Requires-Dist: types-simplejson ; extra == "test"
Requires-Dist: pytest >=6.0 ; extra == "test"
Requires-Dist: pytest-cov ; extra == "test"
Requires-Dist: pytest-pydocstyle ; extra == "test"
Requires-Dist: toml ~=0.10.2 ; extra == "test"
Project-URL: Documentation, https://api.byteblower.com/test-framework/index.html#documentation
Project-URL: Examples, https://api.byteblower.com/test-framework/index.html#examples
Project-URL: Homepage, https://www.byteblower.com
Project-URL: Support Portal, https://support.excentis.com
Provides-Extra: dev
Provides-Extra: docs-dev
Provides-Extra: test
